{"_type":"export","__export_format":4,"__export_date":"2021-12-06T11:34:43.548Z","__export_source":"insomnia.desktop.app:v2021.6.0","resources":[{"_id":"req_6d08bd8c491345f7908240fd0a0173f3","parentId":"fld_02ee4ffba0e3407bb90031faa6031411","modified":1638623684723,"created":1638531704425,"url":"{{ _.url }}\\gerentes","name":"gerentesNovo","description":"","method":"POST","body":{"mimeType":"application/json","text":"{\n\t\"ger_nome\": \"Falcão\",\n\t\"ger_apelido\": \"F\",\n\t\"ger_telefone\": \"99842-9826\",\n\t\"ger_banco\": \"Inter\"\n}"},"parameters":[],"headers":[{"name":"Content-Type","value":"application/json","id":"pair_1c0a7d10b9b74838a95e21db881478cd"}],"authentication":{},"metaSortKey":-1638531704525,"isPrivate":false,"settingStoreCookies":true,"settingSendCookies":true,"settingDisableRenderRequestBody":false,"settingEncodeUrl":true,"settingRebuildPath":true,"settingFollowRedirects":"global","_type":"request"},{"_id":"fld_02ee4ffba0e3407bb90031faa6031411","parentId":"wrk_cac9c9449874466c892d4da3851514c7","modified":1638531715594,"created":1638531715594,"name":"gerente","description":"","environment":{},"environmentPropertyOrder":null,"metaSortKey":-1638531715594,"_type":"request_group"},{"_id":"wrk_cac9c9449874466c892d4da3851514c7","parentId":null,"modified":1638531435101,"created":1638531404300,"name":"sistemaBancario_INSOMNIA","description":"","scope":"collection","_type":"workspace"},{"_id":"req_acbdd0fa5e93435d91594bdd8950b68a","parentId":"fld_02ee4ffba0e3407bb90031faa6031411","modified":1638623684407,"created":1638531691665,"url":"{{ _.url }}\\gerentes\\4","name":"gerentesEditar","description":"","method":"PUT","body":{"mimeType":"application/json","text":"{\n\t\"ger_codigo\": 5,\n\t\"ger_nome\": \"fesfsef\",\n\t\"ger_apelido\": \"G\",\n\t\"ger_telefone\": \"96411-1696\",\n\t\"ger_banco\": \"C621123\"\n}"},"parameters":[],"headers":[{"name":"Content-Type","value":"application/json","id":"pair_83979deeda904d58b42f7d3fbc01d746"}],"authentication":{},"metaSortKey":-1638531704475,"isPrivate":false,"settingStoreCookies":true,"settingSendCookies":true,"settingDisableRenderRequestBody":false,"settingEncodeUrl":true,"settingRebuildPath":true,"settingFollowRedirects":"global","_type":"request"},{"_id":"req_8bafc649776b4cfaa1b88b6c498913ea","parentId":"fld_02ee4ffba0e3407bb90031faa6031411","modified":1638621523887,"created":1638531677881,"url":"{{ _.url }}\\gerentes\\4","name":"gerentesGetById","description":"","method":"GET","body":{},"parameters":[],"headers":[],"authentication":{},"metaSortKey":-1638531704456.25,"isPrivate":false,"settingStoreCookies":true,"settingSendCookies":true,"settingDisableRenderRequestBody":false,"settingEncodeUrl":true,"settingRebuildPath":true,"settingFollowRedirects":"global","_type":"request"},{"_id":"req_c02c3732a89044639eb15f6c621ca5e7","parentId":"fld_02ee4ffba0e3407bb90031faa6031411","modified":1638623665090,"created":1638623568513,"url":"{{ _.url }}\\gerentes\\1","name":"gerentesDelById","description":"","method":"DELETE","body":{},"parameters":[],"headers":[],"authentication":{},"metaSortKey":-1638531704453.125,"isPrivate":false,"settingStoreCookies":true,"settingSendCookies":true,"settingDisableRenderRequestBody":false,"settingEncodeUrl":true,"settingRebuildPath":true,"settingFollowRedirects":"global","_type":"request"},{"_id":"req_2ccf38809f7d48ce98d161e8f2cc571a","parentId":"fld_02ee4ffba0e3407bb90031faa6031411","modified":1638539892090,"created":1638531451669,"url":"{{ _.url }}\\gerentes","name":"gerentesGetAll","description":"","method":"GET","body":{},"parameters":[],"headers":[],"authentication":{},"metaSortKey":-1638531704437.5,"isPrivate":false,"settingStoreCookies":true,"settingSendCookies":true,"settingDisableRenderRequestBody":false,"settingEncodeUrl":true,"settingRebuildPath":true,"settingFollowRedirects":"global","_type":"request"},{"_id":"req_be0dbd39a23a4ee59a4f81553af682ce","parentId":"fld_82d3616f59b74f4085187848ea6cd51e","modified":1638790454733,"created":1638531750218,"url":"{{ _.url }}\\ccorrentes","name":"ccorrentesNovo","description":"","method":"POST","body":{"mimeType":"application/json","text":"{\n\t\"cco_nrconta\": \"123\",\n\t\"cco_tipo\": \"Corrente\",\n\t\"cco_saldo\": 400.32,\n\t\"cco_abertura\": 24,\n\t\"ger_codigo\": 1\n}"},"parameters":[],"headers":[{"name":"Content-Type","value":"application/json","id":"pair_8da6b296d03c42d7a98bcbe3274a80ce"}],"authentication":{},"metaSortKey":-1638531704525,"isPrivate":false,"settingStoreCookies":true,"settingSendCookies":true,"settingDisableRenderRequestBody":false,"settingEncodeUrl":true,"settingRebuildPath":true,"settingFollowRedirects":"global","_type":"request"},{"_id":"fld_82d3616f59b74f4085187848ea6cd51e","parentId":"wrk_cac9c9449874466c892d4da3851514c7","modified":1638531750207,"created":1638531750207,"name":"contaCorrente","description":"","environment":{},"environmentPropertyOrder":null,"metaSortKey":-1634451278344.5,"_type":"request_group"},{"_id":"req_d09d3a79a987422ea9e64fe9c4d173e2","parentId":"fld_82d3616f59b74f4085187848ea6cd51e","modified":1638626197305,"created":1638531750215,"url":"{{ _.url }}\\ccorrentes\\4","name":"ccorrentesEditar","description":"","method":"PUT","body":{"mimeType":"application/json","text":"{\n    \"cco_codigo\": 5,\n    \"cco_nrconta\": \"123\",\n    \"cco_tipo\": \"Correndddte\",\n    \"cco_saldo\": 999.32,\n    \"cco_abertura\": 24,\n    \"ger_codigo\": 1\n  }"},"parameters":[],"headers":[{"name":"Content-Type","value":"application/json","id":"pair_e40ce7835cc049f7abbfdaab74059e1f"}],"authentication":{},"metaSortKey":-1638531704475,"isPrivate":false,"settingStoreCookies":true,"settingSendCookies":true,"settingDisableRenderRequestBody":false,"settingEncodeUrl":true,"settingRebuildPath":true,"settingFollowRedirects":"global","_type":"request"},{"_id":"req_d6ac75a133d64262acbd3855d3795435","parentId":"fld_82d3616f59b74f4085187848ea6cd51e","modified":1638625011428,"created":1638531750213,"url":"{{ _.url }}\\ccorrentes\\5","name":"ccorrentesGetById","description":"","method":"GET","body":{},"parameters":[],"headers":[],"authentication":{},"metaSortKey":-1638531704450,"isPrivate":false,"settingStoreCookies":true,"settingSendCookies":true,"settingDisableRenderRequestBody":false,"settingEncodeUrl":true,"settingRebuildPath":true,"settingFollowRedirects":"global","_type":"request"},{"_id":"req_a1dcfd5b78034c31bfd8304fe34f0f5e","parentId":"fld_82d3616f59b74f4085187848ea6cd51e","modified":1638623632049,"created":1638623597545,"url":"{{ _.url }}\\ccorrentes\\1","name":"ccorrentesDelById","description":"","method":"DELETE","body":{},"parameters":[],"headers":[],"authentication":{},"metaSortKey":-1638531704443.75,"isPrivate":false,"settingStoreCookies":true,"settingSendCookies":true,"settingDisableRenderRequestBody":false,"settingEncodeUrl":true,"settingRebuildPath":true,"settingFollowRedirects":"global","_type":"request"},{"_id":"req_a254d4527bc64b13992a34a5f76db9c5","parentId":"fld_82d3616f59b74f4085187848ea6cd51e","modified":1638540447584,"created":1638531750210,"url":"{{ _.url }}\\ccorrentes","name":"ccorrentesGetAll","description":"","method":"GET","body":{},"parameters":[],"headers":[],"authentication":{},"metaSortKey":-1638531704437.5,"isPrivate":false,"settingStoreCookies":true,"settingSendCookies":true,"settingDisableRenderRequestBody":false,"settingEncodeUrl":true,"settingRebuildPath":true,"settingFollowRedirects":"global","_type":"request"},{"_id":"env_158b2bba214ffb6885ce7ba5436d5e85a714861f","parentId":"wrk_cac9c9449874466c892d4da3851514c7","modified":1638531600173,"created":1638531404316,"name":"Base Environment","data":{"url":"http://localhost:3001"},"dataPropertyOrder":{"&":["url"]},"color":null,"isPrivate":false,"metaSortKey":1638531404316,"_type":"environment"},{"_id":"jar_158b2bba214ffb6885ce7ba5436d5e85a714861f","parentId":"wrk_cac9c9449874466c892d4da3851514c7","modified":1638531404321,"created":1638531404321,"name":"Default Jar","cookies":[],"_type":"cookie_jar"},{"_id":"spc_e86777dbe34649ad8028fb161a4494ed","parentId":"wrk_cac9c9449874466c892d4da3851514c7","modified":1638531404302,"created":1638531404302,"fileName":"sistemaBancario","contents":"","contentType":"yaml","_type":"api_spec"}]}